zenpy/__init__.py
zenpy/lib/__init__.py
zenpy/lib/api.py
zenpy/lib/cache.py
zenpy/lib/endpoint.py
zenpy/lib/exception.py
zenpy/lib/generator.py
zenpy/lib/mapping.py
zenpy/lib/proxy.py
zenpy/lib/request.py
zenpy/lib/response.py
zenpy/lib/util.py
zenpy/lib/api_objects/__init__.py
zenpy/lib/api_objects/chat_objects.py
zenpy/lib/api_objects/help_centre_objects.py
zenpy/lib/api_objects/talk_objects.py
zenpy/lib/api_objects/zis_objects.py
zenpycbp-2.0.27.dist-info/LICENSE
zenpycbp-2.0.27.dist-info/METADATA
zenpycbp-2.0.27.dist-info/WHEEL
zenpycbp-2.0.27.dist-info/top_level.txt
zenpycbp-2.0.27.dist-info/RECORD
