Metadata-Version: 2.1
Name: zenpycbp
Version: 2.0.27
Summary: Python wrapper for the Zendesk API
Home-page: https://github.com/bersama-sama/zenpycbp
Author: Amanda Yang
Author-email: github@bersama.com
License: GPLv3
Download-URL: https://github.com/bersama-sama/zenpycbp/releases/tag/2.0.27
Keywords: zendesk,api,wrapper
Platform: UNKNOWN
Classifier: Development Status :: 5 - Production/Stable
Classifier: Intended Audience :: Developers
Classifier: Intended Audience :: Information Technology
Classifier: Intended Audience :: System Administrators
Classifier: Programming Language :: Python :: 2
Classifier: Programming Language :: Python :: 2.7
Classifier: Programming Language :: Python :: 3
Classifier: Programming Language :: Python :: 3.5
Classifier: Programming Language :: Python :: 3.6
Classifier: Programming Language :: Python :: 3.7
Classifier: Programming Language :: Python :: 3.8
Classifier: Programming Language :: Python :: 3.9
Classifier: License :: OSI Approved :: GNU General Public License v3 (GPLv3)
Classifier: Natural Language :: English
Requires-Dist: requests (>=2.14.2)
Requires-Dist: python-dateutil (>=2.7.5)
Requires-Dist: cachetools (>=3.1.0)
Requires-Dist: pytz (>=2018.9)
Requires-Dist: six (>=1.14.0)
